EtnaAPI/Activities.py
EtnaAPI/Authentication.py
EtnaAPI/Checklists.py
EtnaAPI/Conversations.py
EtnaAPI/Errors.py
EtnaAPI/Files.py
EtnaAPI/Groups.py
EtnaAPI/Marks.py
EtnaAPI/Modules.py
EtnaAPI/Moulinettes.py
EtnaAPI/Quests.py
EtnaAPI/Session.py
EtnaAPI/Student.py
EtnaAPI/Todos.py
EtnaAPI/__init__.py
EtnaAPI-1.0.7.dist-info/LICENSE
EtnaAPI-1.0.7.dist-info/METADATA
EtnaAPI-1.0.7.dist-info/WHEEL
EtnaAPI-1.0.7.dist-info/top_level.txt
EtnaAPI-1.0.7.dist-info/RECORD
