Metadata-Version: 2.1
Name: EtnaAPI
Version: 1.0.7
Summary: Python wrapper to make calls to the Etna's API
Home-page: https://github.com/etna-alternance/EtnaAPI
Author: Clément Doumergue
Author-email: doumer_c@etna-alternance.net
License: UNKNOWN
Platform: UNKNOWN
Classifier: Programming Language :: Python :: 3
Classifier: License :: OSI Approved :: MIT License
Classifier: Operating System :: OS Independent
Requires-Dist: requests
